encord_active/__init__.py
encord_active/cli/__init__.py
encord_active/cli/app_config.py
encord_active/cli/config.py
encord_active/cli/imports.py
encord_active/cli/main.py
encord_active/cli/metric.py
encord_active/cli/print.py
encord_active/cli/project.py
encord_active/cli/utils/__init__.py
encord_active/cli/utils/coco.py
encord_active/cli/utils/decorators.py
encord_active/cli/utils/encord.py
encord_active/cli/utils/prints.py
encord_active/cli/utils/server.py
encord_active/cli/utils/typer.py
encord_active/db/__init__.py
encord_active/db/alembic.ini
encord_active/db/enums.py
encord_active/db/metrics.py
encord_active/db/migrations/README
encord_active/db/migrations/env.py
encord_active/db/migrations/script.py.mako
encord_active/db/migrations/versions/1bdba1540905_init.py
encord_active/db/migrations/versions/bcfdfc2f498a_init2.py
encord_active/db/models.py
encord_active/db/scripts/__init__.py
encord_active/db/scripts/delete_project.py
encord_active/db/scripts/migrate_disk_to_db.py
encord_active/frontend/__init__.py
encord_active/frontend/dist/packaged/assets/annotations-278aa65e.svg
encord_active/frontend/dist/packaged/assets/classes-d8759926.svg
encord_active/frontend/dist/packaged/assets/default_project_image-d39f461e.webp
encord_active/frontend/dist/packaged/assets/empty-aab39c98.svg
encord_active/frontend/dist/packaged/assets/encord-import-1cb3a664.svg
encord_active/frontend/dist/packaged/assets/file-image-f807a638.svg
encord_active/frontend/dist/packaged/assets/import-b86d8e5d.svg
encord_active/frontend/dist/packaged/assets/index-48ccc207.css
encord_active/frontend/dist/packaged/assets/index-d4598704.js
encord_active/frontend/dist/packaged/favicon.ico
encord_active/frontend/dist/packaged/index.html
encord_active/frontend/dist/production/assets/annotations-278aa65e.svg
encord_active/frontend/dist/production/assets/classes-d8759926.svg
encord_active/frontend/dist/production/assets/default_project_image-d39f461e.webp
encord_active-0.1.83.dist-info/LICENSE
encord_active-0.1.83.dist-info/METADATA
encord_active-0.1.83.dist-info/WHEEL
encord_active-0.1.83.dist-info/entry_points.txt
encord_active-0.1.83.dist-info/RECORD
