Metadata-Version: 2.1
Name: encord-active
Version: 0.1.83
Summary: Enable users to improve machine learning models in an active learning fashion via data, label, and model quality.
Home-page: https://encord.com/encord-active/
License: Apache-2.0
Keywords: encord,active,machine,learning,data,label,model,quality,test
Author: Cord Technologies Limited
Author-email: hello@encord.com
Requires-Python: >=3.9, !=2.7.*, !=3.0.*, !=3.1.*, !=3.2.*, !=3.3.*, !=3.4.*, !=3.5.*, !=3.6.*, !=3.7.*, !=3.8.*
Classifier: Environment :: Console
Classifier: Environment :: Web Environment
Classifier: Intended Audience :: Developers
Classifier: Intended Audience :: Education
Classifier: Intended Audience :: Information Technology
Classifier: Intended Audience :: Science/Research
Classifier: License :: OSI Approved :: Apache Software License
Classifier: Operating System :: OS Independent
Classifier: Programming Language :: Python :: 3
Classifier: Programming Language :: Python :: 3.9
Classifier: Programming Language :: Python :: 3.10
Classifier: Programming Language :: Python :: 3.11
Classifier: Topic :: Scientific/Engineering
Classifier: Topic :: Scientific/Engineering :: Artificial Intelligence
Classifier: Topic :: Scientific/Engineering :: Information Analysis
Classifier: Topic :: Software Development
Classifier: Topic :: Software Development :: Quality Assurance
Provides-Extra: coco
Provides-Extra: notebooks
Requires-Dist: PyYAML (>=6.0,<7.0)
Requires-Dist: alembic (>=1.11.1,<2.0.0)
Requires-Dist: av (>=10.0.0,<11.0.0)
Requires-Dist: cachetools (>=5.3.1,<6.0.0)
Requires-Dist: clip-ea (>=1.0,<2.0)
Requires-Dist: encord (>=0.1.95,<0.2.0)
Requires-Dist: fastapi (>=0.95.2,<0.96.0)
Requires-Dist: ftfy (>=6.1.1,<7.0.0)
Requires-Dist: inquirerpy (>=0.3.4,<0.4.0)
Requires-Dist: ipywidgets (>=8.0.4,<9.0.0) ; extra == "notebooks"
Requires-Dist: jupyterlab (>=3.5.2,<4.0.0) ; extra == "notebooks"
Requires-Dist: llvmlite (>=0.40.0,<0.41.0)
Requires-Dist: loguru (>=0.6.0,<0.7.0)
Requires-Dist: matplotlib (>=3.5.3,<4.0.0)
Requires-Dist: natsort (>=8.1.0,<9.0.0)
Requires-Dist: nodejs-bin (>=16.15.1a4,<17.0.0)
Requires-Dist: numpy (>=1.23.5,<1.24.0)
Requires-Dist: opencv-python (==4.5.5.64)
Requires-Dist: orjson (>=3.9.0,<4.0.0)
Requires-Dist: pandas (>=1.4.3,<2.0.0)
Requires-Dist: pandera[mypy] (>=0.15.1,<0.16.0)
Requires-Dist: plotly (>=5.10.0,<6.0.0)
Requires-Dist: poethepoet (>=0.16.5,<0.17.0)
Requires-Dist: prisma (>=0.8.2,<0.9.0)
Requires-Dist: psutil (>=5.9.4,<6.0.0)
Requires-Dist: pycocotools (>=2.0.6,<3.0.0) ; extra == "coco"
Requires-Dist: pydantic (>=1.10.2,<2.0.0)
Requires-Dist: pyjwt (>=2.7.0,<3.0.0)
Requires-Dist: python-dotenv (>=0.21.0,<0.22.0)
Requires-Dist: python-multipart (>=0.0.6,<0.0.7)
Requires-Dist: pytz (>=2022.2.1,<2023.0.0)
Requires-Dist: regex (>=2023.5.5,<2024.0.0)
Requires-Dist: rich (>=12.6.0,<13.0.0)
Requires-Dist: scikit-learn (>=1.0.1,<2.0.0)
Requires-Dist: scipy (==1.10.1)
Requires-Dist: shapely (>=1.7.0,<2.0.0)
Requires-Dist: sqlmodel (>=0.0.8,<0.0.9)
Requires-Dist: termcolor (>=2.0.1,<3.0.0)
Requires-Dist: toml (>=0.10.2,<0.11.0)
Requires-Dist: torch (>=2.0.0,<3.0.0)
Requires-Dist: torchvision (>=0.15.2,<0.16.0)
Requires-Dist: typer (>=0.6.1,<0.7.0)
Requires-Dist: types-cachetools (>=5.3.0.6,<6.0.0.0)
Requires-Dist: types-pytz (>=2022.2.1,<2023.0.0)
Requires-Dist: umap-learn (>=0.5.3,<0.6.0)
Requires-Dist: uvicorn[standard] (>=0.21.1,<0.22.0)
Requires-Dist: watchdog (>=2.1.9,<3.0.0)
Project-URL: Documentation, https://docs.encord.com/docs/active-overview
Project-URL: Repository, https://github.com/encord-team/encord-active
